gracula
