Metadata-Version: 2.1
Name: gracula
Version: 1.0.2
Summary: Gracula is a very simple Twitter api. This package can be done without OAuth.
Home-page: https://github.com/yuutakojima/gracula
Author: yutakojima
Author-email: info@idea-tools.space
License: MIT
Keywords: python twitter api
Platform: UNKNOWN
Classifier: License :: OSI Approved :: MIT License
Classifier: Programming Language :: Python :: 3.6
